xchangelib/__init__.py
xchangelib/service_pb2.py
xchangelib/service_pb2_grpc.py
xchangelib/setup.py
xchangelib/xchange_client.py
xchangelib/docs/source/conf.py
xchangelib/examples/example_bot.py
xchangelib-0.0.8.dist-info/LICENSE
xchangelib-0.0.8.dist-info/METADATA
xchangelib-0.0.8.dist-info/WHEEL
xchangelib-0.0.8.dist-info/top_level.txt
xchangelib-0.0.8.dist-info/RECORD
